{

    "header": {
        "home":"Inicio",
        "about_us":"Nosotros",
        "gallery":"Galería",
        "contact_us":"Contacto",
        "book_now":"Reserva Ahora"
    },
    "footer":{
        "contact_info":{
            "title":"Contactanos",
            "ul":[
                {
                    "li":"Pregúntame lo que quieras ... Estoy aquí para cualquier pregunta que tengas."
                },                
                {
                    "li":"San José del Cabo, Baja California Sur, México."
                },
                {
                    "li":"Oficina 624-110-41-85"
                },
                {
                    "li":"Móvil 624-161-15-48 / 624-157-80-43"
                },
                {
                    "li":"info@cabodriver.com"
                }
            ]
        },
        "send_mail":{
            "title":"Envíanos un email"
        }
    }
}